{"_path":"/blog","_dir":"","_draft":false,"_partial":false,"_locale":"en","_empty":false,"title":"Blog","description":"Blog - CondorHero","excerpt":{"type":"root","children":[{"type":"element","tag":"list-posts","props":{},"children":[]}]},"body":{"type":"root","children":[{"type":"element","tag":"list-posts","props":{},"children":[]}],"toc":{"title":"","searchDepth":2,"depth":2,"links":[]}},"_type":"markdown","_id":"content:1.blog:index.md","_source":"content","_file":"1.blog/index.md","_extension":"md"}